database_utils/__init__.py
database_utils/core/__init__.py
database_utils/core/database_connection.py
database_utils/core/model_repository.py
pyutils_sqlmodel-0.2.4.dist-info/LICENSE.txt
pyutils_sqlmodel-0.2.4.dist-info/METADATA
pyutils_sqlmodel-0.2.4.dist-info/WHEEL
pyutils_sqlmodel-0.2.4.dist-info/top_level.txt
pyutils_sqlmodel-0.2.4.dist-info/RECORD
