Metadata-Version: 2.2
Name: pyutils-sqlmodel
Version: 0.2.4
Summary: Configuracion inicial hacia conexion a base de datos con SQLModel y un repositorio con las operaciones CRUD utilizando genericos para el ahorro de codigo
Author: Christian Carballo Cano
Maintainer: Christian Carballo Cano
Maintainer-email: c.cano2908@outlook.com
Requires-Python: >=3.6
License-File: LICENSE.txt
Requires-Dist: python-dotenv==1.0.1
Requires-Dist: psycopg2-binary==2.9.10
Requires-Dist: setuptools==75.6.0
Requires-Dist: sqlmodel==0.0.22
Dynamic: author
Dynamic: description
Dynamic: description-content-type
Dynamic: maintainer
Dynamic: maintainer-email
Dynamic: requires-dist
Dynamic: requires-python
Dynamic: summary
